OdooTools/__init__.py
OdooTools/utilities/__init__.py
OdooTools/utilities/attachments/__init__.py
OdooTools/utilities/attachments/attachment.py
OdooTools/utilities/datetime/__init__.py
OdooTools/utilities/debug/__init__.py
OdooTools/utilities/debug/debug.py
OdooTools/utilities/records/__init__.py
OdooTools/utilities/records/records.py
odoo_utilities-0.2.dist-info/LICENSE
odoo_utilities-0.2.dist-info/METADATA
odoo_utilities-0.2.dist-info/WHEEL
odoo_utilities-0.2.dist-info/top_level.txt
odoo_utilities-0.2.dist-info/RECORD
