Metadata-Version: 2.1
Name: odoo-utilities
Version: 0.2
Summary: Set of tools for Odoo ERP
Home-page: https://github.com/divad1196/odoo_utilities
Author: Gallay David
Author-email: davidtennis96@hotmail.com
License: UNKNOWN
Platform: UNKNOWN
Classifier: Programming Language :: Python :: 3
Classifier: License :: OSI Approved :: GNU Affero General Public License v3
Classifier: Operating System :: OS Independent
